cms_perf/__init__.py
cms_perf/__main__.py
cms_perf/report.py
cms_perf/sensors/__init__.py
cms_perf/sensors/net_load.py
cms_perf/sensors/sensor.py
cms_perf/sensors/xrd_load.py
cms_perf/setup/__init__.py
cms_perf/setup/cli.py
cms_perf/setup/cli_parser.py
cms_perf-1.1.0.dist-info/entry_points.txt
cms_perf-1.1.0.dist-info/WHEEL
cms_perf-1.1.0.dist-info/METADATA
cms_perf-1.1.0.dist-info/RECORD
