Metadata-Version: 2.1
Name: cms_perf
Version: 1.1.0
Summary: Sensor for the XRootD cms.perf directive
Home-page: https://github.com/maxfischer2781/cms_perf
Keywords: xrootd cms.perf
Author: Max Fischer
Author-email: maxfischer2781@gmail.com
Classifier: Development Status :: 5 - Production/Stable
Classifier: Intended Audience :: System Administrators
Classifier: License :: OSI Approved :: MIT License
Classifier: Programming Language :: Python :: 3 :: Only
Requires-Dist: psutil >=5.6.2
Requires-Dist: pyparsing
Requires-Dist: sphinx ; extra == "doc"
Requires-Dist: sphinx-tabs ; extra == "doc"
Requires-Dist: pytest ; extra == "test"
Requires-Dist: coverage ; extra == "test"
Requires-Dist: pytest-cov ; extra == "test"
Requires-Dist: codecov ; extra == "test"
Requires-Dist: flake8 ; extra == "test"
Requires-Dist: flake8-bugbear ; extra == "test"
Requires-Dist: black >= 24.4.0 ; extra == "test"
Requires-Dist: setproctitle ; extra == "test"
Provides-Extra: doc
Provides-Extra: test
